clipboard_formatter-1.0.dist-info/METADATA
clipboard_formatter-1.0.dist-info/RECORD
clipboard_formatter-1.0.dist-info/WHEEL
clipboard_formatter-1.0.dist-info/entry_points.txt
clipboard_formatter-1.0.dist-info/top_level.txt
clipform/__init__.py
clipform/clipform.py
clipform/command_line.py
