Metadata-Version: 2.1
Name: clipboard-formatter
Version: 1.0
Summary: Takes copied text and formats to be used in SQL list
Home-page: https://github.com/usolek/simple-utils
Author: Ulysses Olek
Author-email: uskovolek@gmail.com
License: MIT
Platform: UNKNOWN
Requires-Dist: pyperclip
